pyconnora/__init__.py
pyconnora/connection.py
pyconnora/test.py
pyconnora-1.0.1.dist-info/METADATA
pyconnora-1.0.1.dist-info/WHEEL
pyconnora-1.0.1.dist-info/top_level.txt
pyconnora-1.0.1.dist-info/RECORD
