Metadata-Version: 2.4
Name: pyconnora
Version: 1.0.1
Summary: A simplified Python library for ORACLE sql operations.
Author-email: Josephus <orca099210@gmail.com>
License-Expression: MIT
Keywords: oracle,database,connection
Requires-Python: >=3.10
Requires-Dist: cx_Oracle
Requires-Dist: dotenv
